MANIFEST.in
README.md
VERSION.txt
setup.cfg
setup.py
definitions/belcarra-acm-ecm.json
definitions/belcarra-acm-eem.json
definitions/belcarra-acm-rndis.json
definitions/belcarra-acm.json
definitions/belcarra-eem-acm.json
docs/README-Gadget.md
docs/README-Raspbian.md
service/gadget.service
service/gadget.start
service/gadget.stop
service/override.conf
src/gadgetapp/__init__.py
src/gadgetconfig/__init__.py
src/gadgetconfig/add.py
src/gadgetconfig/export.py
src/gadgetconfig/manage.py
src/gadgetconfig/prettyjson.py
src/gadgetconfig/remove.py
src/gadgetconfig.egg-info/PKG-INFO
src/gadgetconfig.egg-info/SOURCES.txt
src/gadgetconfig.egg-info/dependency_links.txt
src/gadgetconfig.egg-info/entry_points.txt
src/gadgetconfig.egg-info/requires.txt
src/gadgetconfig.egg-info/top_level.txt