Metadata-Version: 2.1
Name: gadgetconfig
Version: 0.0.25
Summary: gadgetconfig creates and controls Gadget USB Devices and integrates Gadget with systemd
Home-page: http://github.com/Belarra/gadgetconfig
Author: Stuart Lynne
Author-email: stuart.lynne@belcarra.com
License: MIT
Download-URL: http://github.com/Belarra/gadgetconfig.git
Keywords: usb,gadget
Platform: UNKNOWN
Classifier: Programming Language :: Python
Classifier: Development Status :: 3 - Alpha
Classifier: Environment :: Console
Classifier: Intended Audience :: Developers
Classifier: Intended Audience :: System Administrators
Classifier: Operating System :: POSIX
Classifier: License :: OSI Approved :: MIT License
Classifier: Natural Language :: English
Classifier: Topic :: System :: System Shells
Classifier: Topic :: System :: Systems Administration
